runecrypt/__init__.py
runecrypt/utils.py
runecrypt-0.1.dist-info/METADATA
runecrypt-0.1.dist-info/WHEEL
runecrypt-0.1.dist-info/top_level.txt
runecrypt-0.1.dist-info/RECORD
