Metadata-Version: 2.1
Name: runecrypt
Version: 0.1
Summary: Crypt tools based on runic alphabet and random keys
Home-page: https://github.com/luks3r/runecrypt
Author: luks3r
Author-email: UNKNOWN
License: GNU
Platform: UNKNOWN
